chem_mrl/__init__.py
chem_mrl/constants.py
chem_mrl/load.py
chem_mrl/molecular_embedder.py
chem_mrl/molecular_fingerprinter.py
chem_mrl/similarity_functions.py
chem_mrl/util.py
chem_mrl/benchmark/DatabaseBenchmark.py
chem_mrl/benchmark/__init__.py
chem_mrl/conf/base.yaml
chem_mrl/conf/evaluate_precision.yaml
chem_mrl/conf/genmol.yaml
chem_mrl/conf/model/chem_2d_mrl.yaml
chem_mrl/conf/model/chem_mrl.yaml
chem_mrl/conf/model/classifier.yaml
chem_mrl/conf/model/dice_loss_classifier.yaml
chem_mrl/evaluation/EmbeddingSimilarityEvaluator.py
chem_mrl/evaluation/LabelAccuracyEvaluator.py
chem_mrl/evaluation/__init__.py
chem_mrl/evaluation/utils.py
chem_mrl/losses/ClassifierLoss.py
chem_mrl/losses/TanimotoLoss.py
chem_mrl/losses/__init__.py
chem_mrl/models/MaxPoolBERT.py
chem_mrl/models/__init__.py
chem_mrl/schemas/BaseConfig.py
chem_mrl/schemas/ChemMRLConfig.py
chem_mrl/schemas/ClassifierConfig.py
chem_mrl/schemas/DatasetConfig.py
chem_mrl/schemas/Enums.py
chem_mrl/schemas/MaxPoolBERTConfig.py
chem_mrl/schemas/__init__.py
chem_mrl/trainers/BaseTrainer.py
chem_mrl/trainers/ChemMrlTrainer.py
chem_mrl/trainers/ClassifierTrainer.py
chem_mrl/trainers/TrainerExecutor.py
chem_mrl/trainers/__init__.py
chem_mrl-0.8.3.dist-info/licenses/LICENSE
chem_mrl-0.8.3.dist-info/METADATA
chem_mrl-0.8.3.dist-info/WHEEL
chem_mrl-0.8.3.dist-info/top_level.txt
chem_mrl-0.8.3.dist-info/RECORD
