Metadata-Version: 2.4
Name: chem-mrl
Version: 0.8.3
Summary: SMILES-based Matryoshka Representation Learning Embedding Model
Author-email: Emmanuel Cortes <manny@derifyai.com>
Maintainer-email: Emmanuel Cortes <manny@derifyai.com>
License: Apache 2.0
Project-URL: Repository, https://github.com/emapco/chem-mrl
Project-URL: Homepage, https://github.com/emapco/chem-mrl
Project-URL: Documentation, https://github.com/emapco/chem-mrl#readme
Project-URL: Bug Tracker, https://github.com/emapco/chem-mrl/issues
Project-URL: Changelog, https://github.com/emapco/chem-mrl/releases
Keywords: cheminformatics,machine-learning,transformers,smiles,embeddings,matryoshka-representation-learning
Classifier: Development Status :: 5 - Production/Stable
Classifier: Intended Audience :: Science/Research
Classifier: Intended Audience :: Developers
Classifier: Operating System :: OS Independent
Classifier: License :: OSI Approved :: Apache Software License
Classifier: Programming Language :: Python :: 3
Classifier: Programming Language :: Python :: 3.10
Classifier: Programming Language :: Python :: 3.11
Classifier: Programming Language :: Python :: 3.12
Classifier: Programming Language :: Python :: 3.13
Classifier: Topic :: Scientific/Engineering :: Chemistry
Classifier: Topic :: Scientific/Engineering :: Artificial Intelligence
Requires-Python: >=3.10
License-File: LICENSE
Requires-Dist: transformers[torch]<5.0.0,>=4.56.1
Requires-Dist: sentence-transformers[train]<6.0.0,>=5.1.0
Requires-Dist: optuna>=4.2.0
Requires-Dist: wandb>=0.19.4
Requires-Dist: torch<=2.9.0,>=2.6.0
Requires-Dist: scikit-learn<2.0.0,>=1.6.1
Requires-Dist: pandas>=2.0.0
Requires-Dist: numpy>=2.0.0
Requires-Dist: hydra-core>=1.3.2
Requires-Dist: einops==0.8.1
Requires-Dist: codecarbon<4.0.0,>=3.0.0
Requires-Dist: datasets<5.0.0,>=3.6.0
Requires-Dist: rdkit==2025.3.6
Requires-Dist: pyarrow==21.0.0
Requires-Dist: torch-optimi>=0.3.2
Provides-Extra: train
Requires-Dist: datasets==3.6.0; extra == "train"
Provides-Extra: dev
Requires-Dist: pytest; extra == "dev"
Requires-Dist: pytest-cov; extra == "dev"
Requires-Dist: pytest-xdist; extra == "dev"
Requires-Dist: pytest-env; extra == "dev"
Requires-Dist: ipykernel; extra == "dev"
Requires-Dist: ipywidgets; extra == "dev"
Requires-Dist: build; extra == "dev"
Requires-Dist: ruff; extra == "dev"
Requires-Dist: ninja; extra == "dev"
Provides-Extra: benchmark
Requires-Dist: sqlalchemy==2.0.41; extra == "benchmark"
Requires-Dist: psycopg2-binary==2.9.10; extra == "benchmark"
Requires-Dist: pgvector==0.4.1; extra == "benchmark"
Provides-Extra: data
Requires-Dist: pandarallel==1.6.5; extra == "data"
Requires-Dist: safe-mol==0.1.14; extra == "data"
Requires-Dist: opencv-python==4.12.0.88; extra == "data"
Requires-Dist: beautifulsoup4==4.14.2; extra == "data"
Dynamic: license-file
